hai/__init__.py
hai/boto3_multipart_upload.py
hai/event_emitter.py
hai/parallel.py
hai/pipe_pump.py
hai/py.typed
hai/rate_limiter.py
hai-0.4.1.dist-info/METADATA
hai-0.4.1.dist-info/WHEEL
hai-0.4.1.dist-info/licenses/LICENSE
hai-0.4.1.dist-info/RECORD
