Metadata-Version: 2.3
Name: hai
Version: 0.4.1
Summary: Toolbelt library
Project-URL: Homepage, https://github.com/valohai/hai
Author-email: Valohai <dev@valohai.com>
License-Expression: MIT
License-File: LICENSE
Requires-Python: >=3.7
